screwmpc_experiments/__init__.py
screwmpc_experiments/_version.py
screwmpc_experiments/_version.pyi
screwmpc_experiments/py.typed
screwmpc_experiments/assets/pivoting.xml
screwmpc_experiments/assets/random.xml
screwmpc_experiments/experiments/__init__.py
screwmpc_experiments/experiments/common.py
screwmpc_experiments/experiments/screwmpc.py
screwmpc_experiments/launchers/__init__.py
screwmpc_experiments/launchers/pivoting.py
screwmpc_experiments/launchers/random.py
screwmpc_experiments/launchers/trigger_grasp.py
screwmpc_experiments-0.4.5.dist-info/METADATA
screwmpc_experiments-0.4.5.dist-info/WHEEL
screwmpc_experiments-0.4.5.dist-info/entry_points.txt
screwmpc_experiments-0.4.5.dist-info/licenses/LICENSE
screwmpc_experiments-0.4.5.dist-info/RECORD
